findpython-0.6.0.dist-info/METADATA
findpython-0.6.0.dist-info/WHEEL
findpython-0.6.0.dist-info/entry_points.txt
findpython-0.6.0.dist-info/licenses/LICENSE
findpython/__init__.py
findpython/__main__.py
findpython/__version__.py
findpython/finder.py
findpython/pep514tools/__init__.py
findpython/pep514tools/__main__.py
findpython/pep514tools/_registry.py
findpython/pep514tools/environment.py
findpython/providers/__init__.py
findpython/providers/asdf.py
findpython/providers/base.py
findpython/providers/macos.py
findpython/providers/path.py
findpython/providers/pyenv.py
findpython/providers/rye.py
findpython/providers/winreg.py
findpython/python.py
findpython/utils.py
findpython-0.6.0.dist-info/RECORD
