Metadata-Version: 2.1
Name: findpython
Version: 0.6.0
Summary: A utility to find python versions on your system
Author-Email: Frost Ming <mianghong@gmail.com>
License: MIT
Classifier: Programming Language :: Python :: 3
Classifier: Programming Language :: Python :: 3.8
Classifier: Programming Language :: Python :: 3.9
Classifier: Programming Language :: Python :: 3.10
Classifier: Programming Language :: Python :: 3.11
Classifier: Programming Language :: Python :: 3.12
Project-URL: Homepage, https://github.com/frostming/findpython
Requires-Python: >=3.8
Requires-Dist: packaging>=20
